MANIFEST.in
README.md
requirements-dev.txt
requirements.txt
setup.cfg
setup.py
version_number.txt
simpyple/__init__.py
simpyple/schedule.py
simpyple.egg-info/PKG-INFO
simpyple.egg-info/SOURCES.txt
simpyple.egg-info/dependency_links.txt
simpyple.egg-info/not-zip-safe
simpyple.egg-info/requires.txt
simpyple.egg-info/top_level.txt