Metadata-Version: 1.1
Name: simpyple
Version: 0.1.10
Summary: A bunch of utilities for simpy
Home-page: https://github.com/thinkingbox/simpyple
Author: Piergiuliano Bossi
Author-email: UNKNOWN
License: UNKNOWN
Keywords: simpy simulation
Platform: UNKNOWN
Classifier: Development Status :: 3 - Alpha
Classifier: Environment :: Console
Classifier: Intended Audience :: Developers
Classifier: Intended Audience :: Education
Classifier: Intended Audience :: Science/Research
Classifier: License :: OSI Approved :: GNU General Public License v3 (GPLv3)
Classifier: Natural Language :: English
Classifier: Operating System :: POSIX :: Linux
Classifier: Programming Language :: Python
Classifier: Programming Language :: Python :: 2.7
Classifier: Topic :: Scientific/Engineering
